analysis/__init__.py
analysis/report_writer.py
analysis/rollback_raster_analysis.py
analysis/rollback_stats.py
analysis/rollback_tabular_stats.py
application/__init__.py
application/app.py
application/cli.py
application/gcbm_input_merge_cli.py
application/log_helper.py
application/rollback_app_parameters.py
application/rollback_case_runner.py
gcbm/__init__.py
gcbm/gcbm_disturbance_sequence_factory.py
gcbm/gcbm_disturbance_type_order.py
gcbm/gcbm_input.py
gcbm/gcbm_input_db.py
gcbm/gcbm_inventory_layer_factory.py
gcbm/gcbm_land_use_change.py
gcbm/gcbm_landscape_factory.py
gcbm/gcbm_output_writer.py
gcbm/gcbm_stand_replacing.py
gcbm/rolled_back_gcbm_input.py
gcbm/merge/__init__.py
gcbm/merge/gcbm_merge.py
gcbm/merge/gcbm_merge_disturbance.py
gcbm/merge/gcbm_merge_index.py
gcbm/merge/gcbm_merge_input_db.py
gcbm/merge/gcbm_merge_inventory.py
gcbm/merge/gcbm_merge_layer_input.py
gcbm/merge/gcbm_merge_layer_output.py
gcbm/merge/gcbm_merge_methods.py
gcbm/merge/gcbm_merge_tile.py
operating_format/__init__.py
operating_format/attribute_layer.py
operating_format/condensed_n_layer_stack.py
operating_format/disturbance_layer.py
operating_format/disturbance_sequence.py
operating_format/disturbance_sequence_factory.py
operating_format/inventory_layer.py
operating_format/inventory_layer_factory.py
operating_format/landscape.py
operating_format/landscape_work_unit.py
operating_format/layer.py
operating_format/numpy_optimization.py
operating_format/output_events.py
operating_format/rollback_inventory.py
operating_format/rollback_output.py
operating_format/spatial_layer.py
operating_format/stacked_disturbance_layer.py
procedures/__init__.py
procedures/age_generator.py
procedures/basic_rollback_procedure.py
procedures/categorical_distribution.py
procedures/categorical_distribution_index.py
procedures/deforestation_pre_process.py
procedures/distribution_age_generator.py
procedures/disturbance_type_generator.py
procedures/no_supporting_info_rollback_procedure.py
spatial_inventory_rollback-1.1.0.dist-info/METADATA
spatial_inventory_rollback-1.1.0.dist-info/WHEEL
spatial_inventory_rollback-1.1.0.dist-info/top_level.txt
spatial_inventory_rollback-1.1.0.dist-info/RECORD
